{
	"info": {
		"_postman_id": "53fe2ebc-fcf9-4ff8-9c04-f9eb17577dd0",
		"name": "YuGames API",
		"description": "This API goal is to monitor players performance across real-world and virtual games.",
		"schema": "https://schema.getpostman.com/json/collection/v2.1.0/collection.json",
		"_exporter_id": "25561894"
	},
	"item": [
		{
			"name": "Admin",
			"item": [
				{
					"name": "Get dashboard stats",
					"request": {
						"method": "GET",
						"header": [],
						"url": {
							"raw": "{{baseUrl}}/admin/dashboard",
							"host": [
								"{{baseUrl}}"
							],
							"path": [
								"admin",
								"dashboard"
							]
						}
					},
					"response": []
				}
			]
		},
		{
			"name": "Tournament",
			"item": [
				{
					"name": "Create",
					"request": {
						"method": "POST",
						"header": [],
						"body": {
							"mode": "raw",
							"raw": "{\n  \"name\": \"Test tournament\",\n  \"description\": \"desc\",\n  \"state\": 0,\n  \"logoUrl\": \"https://media.licdn.com/dms/image/C4E0BAQFpaA1IhSqABA/company-logo_200_200/0/1614341145793?e=2147483647&v=beta&t=QCMXDnCeTeRTRitEmTHFLsBr4DMlQjFGUtKVzPjLhf4\",\n  \"plannedFrom\": \"2023-09-14T10:18:20.445Z\",\n  \"plannedTo\": \"2023-09-15T10:18:20.445Z\"\n}",
							"options": {
								"raw": {
									"language": "json"
								}
							}
						},
						"url": {
							"raw": "{{baseUrl}}/tournament",
							"host": [
								"{{baseUrl}}"
							],
							"path": [
								"tournament"
							]
						}
					},
					"response": []
				},
				{
					"name": "Get All",
					"request": {
						"auth": {
							"type": "noauth"
						},
						"method": "GET",
						"header": [],
						"url": {
							"raw": "{{baseUrl}}/tournament",
							"host": [
								"{{baseUrl}}"
							],
							"path": [
								"tournament"
							]
						}
					},
					"response": []
				}
			]
		},
		{
			"name": "Season",
			"item": [
				{
					"name": "Get current season",
					"request": {
						"auth": {
							"type": "noauth"
						},
						"method": "GET",
						"header": [],
						"url": {
							"raw": "{{baseUrl}}/season/current",
							"host": [
								"{{baseUrl}}"
							],
							"path": [
								"season",
								"current"
							]
						}
					},
					"response": []
				},
				{
					"name": "Get all",
					"request": {
						"auth": {
							"type": "noauth"
						},
						"method": "GET",
						"header": [],
						"url": {
							"raw": "{{baseUrl}}/season",
							"host": [
								"{{baseUrl}}"
							],
							"path": [
								"season"
							]
						}
					},
					"response": []
				}
			]
		},
		{
			"name": "FifaTeam",
			"item": [
				{
					"name": "Get all",
					"request": {
						"auth": {
							"type": "noauth"
						},
						"method": "GET",
						"header": [],
						"url": {
							"raw": "{{baseUrl}}/fifateam/all",
							"host": [
								"{{baseUrl}}"
							],
							"path": [
								"fifateam",
								"all"
							]
						}
					},
					"response": []
				}
			]
		},
		{
			"name": "Game",
			"item": [
				{
					"name": "Get last X played",
					"request": {
						"auth": {
							"type": "noauth"
						},
						"method": "GET",
						"header": [],
						"url": {
							"raw": "{{baseUrl}}/game/last/5",
							"host": [
								"{{baseUrl}}"
							],
							"path": [
								"game",
								"last",
								"5"
							]
						}
					},
					"response": []
				},
				{
					"name": "Get last X played by player",
					"request": {
						"auth": {
							"type": "noauth"
						},
						"method": "GET",
						"header": [],
						"url": {
							"raw": "{{baseUrl}}/game/last/5/player/1",
							"host": [
								"{{baseUrl}}"
							],
							"path": [
								"game",
								"last",
								"5",
								"player",
								"1"
							]
						}
					},
					"response": []
				},
				{
					"name": "Create",
					"request": {
						"method": "POST",
						"header": [],
						"body": {
							"mode": "raw",
							"raw": "{\r\n    \"CreatedOn\": \"2023-08-06T14:29:42\",\r\n    \"KeycloakId\": \"zfzef\",\r\n    \"PlatformId\": 1,\r\n    \"Team1\": [\r\n        \"1\", \"2\"\r\n    ],\r\n    \"TeamCode1\": \"FRA\",\r\n    \"TeamScore1\": 42,\r\n    \"Team2\": [\r\n        \"3\", \"4\"\r\n    ],\r\n    \"TeamCode2\": \"POR\",\r\n    \"TeamScore2\": 0\r\n}",
							"options": {
								"raw": {
									"language": "json"
								}
							}
						},
						"url": {
							"raw": "{{baseUrl}}/game",
							"host": [
								"{{baseUrl}}"
							],
							"path": [
								"game"
							]
						}
					},
					"response": []
				},
				{
					"name": "Update",
					"request": {
						"method": "PATCH",
						"header": [],
						"body": {
							"mode": "raw",
							"raw": "{\r\n    \"Id\": 89,\r\n    \"PlatformId\": 2,\r\n    \"TeamCode1\": \"FCB\",\r\n    \"FifaTeam1\": 21,\r\n    \"TeamScore1\": 2,\r\n    \"TeamCode2\": \"MCI\",\r\n    \"FifaTeam2\": 10,\r\n    \"TeamScore2\": 1\r\n}",
							"options": {
								"raw": {
									"language": "json"
								}
							}
						},
						"url": {
							"raw": "{{baseUrl}}/game",
							"host": [
								"{{baseUrl}}"
							],
							"path": [
								"game"
							]
						}
					},
					"response": []
				},
				{
					"name": "Search games",
					"request": {
						"auth": {
							"type": "noauth"
						},
						"method": "GET",
						"header": [],
						"url": {
							"raw": "{{baseUrl}}/game?limit=10&platformId=1&startDate=2023-06-01T00:00:00&endDate=2023-08-31T00:00:00",
							"host": [
								"{{baseUrl}}"
							],
							"path": [
								"game"
							],
							"query": [
								{
									"key": "limit",
									"value": "10"
								},
								{
									"key": "platformId",
									"value": "1"
								},
								{
									"key": "startDate",
									"value": "2023-06-01T00:00:00"
								},
								{
									"key": "endDate",
									"value": "2023-08-31T00:00:00"
								}
							]
						}
					},
					"response": []
				},
				{
					"name": "Get by ID",
					"request": {
						"auth": {
							"type": "noauth"
						},
						"method": "GET",
						"header": [],
						"url": {
							"raw": "{{baseUrl}}/game/89",
							"host": [
								"{{baseUrl}}"
							],
							"path": [
								"game",
								"89"
							]
						}
					},
					"response": []
				},
				{
					"name": "Delete",
					"request": {
						"method": "DELETE",
						"header": [],
						"url": {
							"raw": "{{baseUrl}}/game/89",
							"host": [
								"{{baseUrl}}"
							],
							"path": [
								"game",
								"89"
							]
						}
					},
					"response": []
				}
			]
		},
		{
			"name": "Highlight",
			"item": [
				{
					"name": "Get all",
					"request": {
						"auth": {
							"type": "noauth"
						},
						"method": "GET",
						"header": [],
						"url": {
							"raw": "{{baseUrl}}/highlight/all",
							"host": [
								"{{baseUrl}}"
							],
							"path": [
								"highlight",
								"all"
							]
						}
					},
					"response": []
				},
				{
					"name": "Get all Copy",
					"request": {
						"method": "POST",
						"header": [],
						"body": {
							"mode": "raw",
							"raw": "{\r\n    \"name\": \"Test create with desc and URL\",\r\n    \"fifaGameId\": 118,\r\n    \"description\": \"this is a desc\",\r\n    \"externalUrl\": \"https://www.google.fr\"\r\n}",
							"options": {
								"raw": {
									"language": "json"
								}
							}
						},
						"url": {
							"raw": "{{baseUrl}}/highlight",
							"host": [
								"{{baseUrl}}"
							],
							"path": [
								"highlight"
							]
						}
					},
					"response": []
				}
			]
		},
		{
			"name": "Platform",
			"item": [
				{
					"name": "Get all",
					"request": {
						"auth": {
							"type": "noauth"
						},
						"method": "GET",
						"header": [],
						"url": {
							"raw": "{{baseUrl}}/platform/all",
							"host": [
								"{{baseUrl}}"
							],
							"path": [
								"platform",
								"all"
							]
						}
					},
					"response": []
				},
				{
					"name": "Create",
					"request": {
						"method": "POST",
						"header": [],
						"body": {
							"mode": "raw",
							"raw": "{\n    \"name\": \"ezefezfezf\"\n}",
							"options": {
								"raw": {
									"language": "json"
								}
							}
						},
						"url": {
							"raw": "{{baseUrl}}/platform",
							"host": [
								"{{baseUrl}}"
							],
							"path": [
								"platform"
							]
						}
					},
					"response": []
				},
				{
					"name": "Update",
					"request": {
						"method": "PATCH",
						"header": [],
						"body": {
							"mode": "raw",
							"raw": "{\n    \"id\": 3,\n    \"name\": \"Xbox\"\n}",
							"options": {
								"raw": {
									"language": "json"
								}
							}
						},
						"url": {
							"raw": "{{baseUrl}}/platform",
							"host": [
								"{{baseUrl}}"
							],
							"path": [
								"platform"
							]
						}
					},
					"response": []
				},
				{
					"name": "Get by ID",
					"request": {
						"auth": {
							"type": "noauth"
						},
						"method": "GET",
						"header": [],
						"url": {
							"raw": "{{baseUrl}}/platform/1",
							"host": [
								"{{baseUrl}}"
							],
							"path": [
								"platform",
								"1"
							]
						}
					},
					"response": []
				}
			]
		},
		{
			"name": "Player",
			"item": [
				{
					"name": "Get current",
					"request": {
						"method": "GET",
						"header": [],
						"url": {
							"raw": "{{baseUrl}}/player/me",
							"host": [
								"{{baseUrl}}"
							],
							"path": [
								"player",
								"me"
							]
						}
					},
					"response": []
				},
				{
					"name": "Update",
					"request": {
						"method": "PATCH",
						"header": [],
						"body": {
							"mode": "raw",
							"raw": "{\r\n    \"FullName\": \"Test update\",\r\n    \"Nickname\": \"The Nickname\",\r\n    \"ProfilePictureUrl\": \"https://kultt.fr/wp-content/uploads/2022/09/RickAstley-ad2022.jpg\"\r\n}",
							"options": {
								"raw": {
									"language": "json"
								}
							}
						},
						"url": {
							"raw": "{{baseUrl}}/player/me",
							"host": [
								"{{baseUrl}}"
							],
							"path": [
								"player",
								"me"
							]
						}
					},
					"response": []
				},
				{
					"name": "Update (Admin only)",
					"request": {
						"method": "PATCH",
						"header": [],
						"body": {
							"mode": "raw",
							"raw": "{\r\n  \"id\": 19,\r\n  \"keycloakId\": \"8c85f712-db75-4529-80a3-97311dacd535\",\r\n  \"fullName\": \"Pierre Henri Bachelain\",\r\n  \"nickname\": \"PH\",\r\n  \"profilePictureUrl\": \"https://static.wikia.nocookie.net/xbox/images/0/05/1_-_1XzYnhZ.png/revision/latest/scale-to-width-down/1000?cb=20210628044343\"\r\n}",
							"options": {
								"raw": {
									"language": "json"
								}
							}
						},
						"url": {
							"raw": "{{baseUrl}}/player",
							"host": [
								"{{baseUrl}}"
							],
							"path": [
								"player"
							]
						}
					},
					"response": []
				},
				{
					"name": "Get by ID",
					"request": {
						"auth": {
							"type": "noauth"
						},
						"method": "GET",
						"header": [],
						"url": {
							"raw": "{{baseUrl}}/player/1",
							"host": [
								"{{baseUrl}}"
							],
							"path": [
								"player",
								"1"
							]
						}
					},
					"response": []
				},
				{
					"name": "Get all",
					"request": {
						"auth": {
							"type": "noauth"
						},
						"method": "GET",
						"header": [],
						"url": {
							"raw": "{{baseUrl}}/player/all",
							"host": [
								"{{baseUrl}}"
							],
							"path": [
								"player",
								"all"
							]
						}
					},
					"response": []
				},
				{
					"name": "Get stats by player",
					"request": {
						"auth": {
							"type": "noauth"
						},
						"method": "GET",
						"header": [],
						"url": {
							"raw": "{{baseUrl}}/player/1/stats?seasonId=",
							"host": [
								"{{baseUrl}}"
							],
							"path": [
								"player",
								"1",
								"stats"
							],
							"query": [
								{
									"key": "seasonId",
									"value": ""
								}
							]
						}
					},
					"response": []
				},
				{
					"name": "Get most teams played",
					"request": {
						"auth": {
							"type": "noauth"
						},
						"method": "GET",
						"header": [],
						"url": {
							"raw": "{{baseUrl}}/player/1/mostplayedteams",
							"host": [
								"{{baseUrl}}"
							],
							"path": [
								"player",
								"1",
								"mostplayedteams"
							]
						}
					},
					"response": []
				}
			]
		}
	],
	"auth": {
		"type": "bearer",
		"bearer": [
			{
				"key": "token",
				"value": "{{token}}",
				"type": "string"
			}
		]
	},
	"event": [
		{
			"listen": "prerequest",
			"script": {
				"type": "text/javascript",
				"exec": [
					""
				]
			}
		},
		{
			"listen": "test",
			"script": {
				"type": "text/javascript",
				"exec": [
					""
				]
			}
		}
	]
}